episode/__init__.py
episode/basis.py
episode/composition_map.py
episode/config.py
episode/constants.py
episode/cubic.py
episode/dataset.py
episode/decision_tree.py
episode/episode.py
episode/gam.py
episode/infinite_motifs.py
episode/optimize_properties.py
episode/property_map.py
episode/semantic_predictor.py
episode/semantic_representation.py
episode/torch_model.py
episode/torch_utils.py
episode/training.py
episode/trajectory_predictor.py
episode/types.py
episode/utils.py
episode_py-0.0.1.dist-info/licenses/LICENSE
episode_py-0.0.1.dist-info/METADATA
episode_py-0.0.1.dist-info/WHEEL
episode_py-0.0.1.dist-info/top_level.txt
episode_py-0.0.1.dist-info/RECORD
