Metadata-Version: 2.4
Name: episode-py
Version: 0.0.1
Author: Krzysztof Kacprzyk
License: MIT License
Project-URL: Homepage, https://github.com/krzysztof-kacprzyk/EPISODEpy
License-File: LICENSE
Requires-Dist: numpy>=1.0.0
Requires-Dist: pandas>=2.0.0
Requires-Dist: scipy>=1.0.0
Requires-Dist: matplotlib>=3.0.0
Requires-Dist: optuna>=3.0.0
Requires-Dist: tqdm>=4.0.0
Requires-Dist: torch>=2.0.0
Requires-Dist: lightning>=2.0.0
Dynamic: license-file
